<resources>

    <style name="Theme.VoiceRoom.Dark" parent="Theme.AUIKit.Dark">
        <item name="windowActionBar">false</item>
        <item name="windowNoTitle">true</item>
        <item name="android:windowBackground">@drawable/voice_bg_app_def_dark</item>
        <item name="android:statusBarColor">@android:color/transparent</item>

        <!-- VoiceRoom -->
        <item name="voice_room_appearance">@style/voice_room_appearance</item>
        <item name="aui_editText_appearance">@style/AUIEditText.Dark</item>
        <item name="aui_alertDialog_appearance_outline">@style/AUIAlertDialog.Dark</item>

        <!--
            voiceRoom 使用主题说明：如果想修改某个组件中的个别属性 可以在style中继承对应组件重新需要修改属性
            如果无需修改 则可直接继承Theme.AUIKit 或 Theme.AUIKit.Dark 使用默认2套主题样式
         -->
<!--        &lt;!&ndash;VoiceRoom Top组件 &ndash;&gt;-->
<!--        <item name="aui_roomInfo_appearance">@style/aui_roomInfo_appearance</item>-->
<!--        <item name="aui_memberInfo_appearance">@style/aui_memberInfo_appearance</item>-->
<!--        &lt;!&ndash;VoiceRoom input组件 &ndash;&gt;-->
<!--        <item name="aui_chatBottomView_appearance">@style/aui_chatBottomView_appearance</item>-->
<!--        <item name="aui_emojiView_appearance">@style/aui_emojiView_appearance</item>-->
<!--        &lt;!&ndash; 弹幕组件 &ndash;&gt;-->
<!--        <item name="aui_chatListView_appearance">@style/aui_chatListView_appearance</item>-->
<!--        &lt;!&ndash; 麦位组件 &ndash;&gt;-->
<!--        <item name="aui_micSeats_appearance">@style/aui_micSeats_appearance</item>-->
<!--        <item name="aui_micSeatItem_appearance">@style/aui_micSeatsItem_appearance</item>-->
<!--        <item name="aui_micSeatDialog_appearance">@style/aui_micSeatsDialog_appearance</item>-->
<!--        &lt;!&ndash; 礼物组件 &ndash;&gt;-->
<!--        <item name="aui_giftBarrage_appearance">@style/aui_giftBarrage_appearance</item>-->
<!--        <item name="aui_giftBottomDialog_appearance">@style/aui_giftBottomDialog_appearance</item>-->
<!--        &lt;!&ndash; 邀请、申请组件 &ndash;&gt;-->
<!--        <item name="aui_action_appearance">@style/aui_action_appearance</item>-->

    </style>

    <style name="AUIEditText.Dark">
        <item name="aui_edittext_input_textColor">#FFFFFF</item>
        <item name="aui_edittext_input_hintTextColor">#5E686E</item>
        <item name="aui_edittext_input_backgroundColor">#2F3437</item>
    </style>

    <style name="AUIAlertDialog.Dark">
        <item name="aui_alertDialog_shadowColor">#171A1C</item>
        <item name="aui_alertDialog_contentBackgroundColor">#171A1C</item>
        <item name="aui_alertDialog_titleTextColor">@android:color/white</item>
        <item name="aui_alertDialog_messageTextColor">@color/aui_white</item>
    </style>


</resources>